{
  "states": [
    {
      "id": "tohu",
      "name": "Тоху",
      "hebrew": "תֹהוּ",
      "paleo": "𐤕𐤅𐤄𐤅",
      "color": "#0a0a0a",
      "physics": "Запертость. Нет входа, нет выхода, нет движения.",
      "intensity": 0.0,
      "intensity_label": "полная неподвижность",
      "paleo_breakdown": [
        { "letter": "ת", "paleo": "𐤕", "name": "Тав", "function": "знак, печать" },
        { "letter": "ו", "paleo": "𐤅", "name": "Вав", "function": "связка, крюк" },
        { "letter": "ה", "paleo": "𐤄", "name": "Хе", "function": "дыхание, откровение" },
        { "letter": "ו", "paleo": "𐤅", "name": "Вав", "function": "связка, крюк" }
      ],
      "paleo_meaning": "Печать (ת) пустого связывания (ו) — дыхания (ה) нет, только связка (ו).",
      "meaning": "Пустота, хаос, первозданное без-образие. Состояние до начала движения.",
      "examples": ["творческий ступор", "замкнутый круг", "депрессивный эпизод"],
      "transitions": [
        { "to": "shamayim", "label": "открыть выход", "action": "Найти первую дверь (Далет) в стене" },
        { "to": "midbar", "label": "начать движение", "action": "Сделать одно маленькое действие в любом направлении" }
      ],
      "diagnostic_questions": [
        { "id": "q_tohu_1", "text": "Чувствуешь ли ты, что застрял и не можешь двинуться?", "weight": { "tohu": 1.0, "hoshekh": 0.3 } },
        { "id": "q_tohu_2", "text": "Есть ли у тебя ощущение, что все выходы закрыты?", "weight": { "tohu": 0.8, "mitzrayim": 0.4 } }
      ]
    },
    {
      "id": "hoshekh",
      "name": "Хошех",
      "hebrew": "חֹשֶׁךְ",
      "paleo": "𐤇𐤔𐤊",
      "color": "#1a1a2e",
      "physics": "Сжатость. Плотность. Непроницаемость. Давление со всех сторон.",
      "intensity": 0.25,
      "intensity_label": "сильное сжатие",
      "paleo_breakdown": [
        { "letter": "ח", "paleo": "𐤇", "name": "Хет", "function": "ограда, отделение" },
        { "letter": "ש", "paleo": "𐤔", "name": "Шин", "function": "зуб, разрушение" },
        { "letter": "ך", "paleo": "𐤊", "name": "Каф (софит)", "function": "ладонь, удержание" }
      ],
      "paleo_meaning": "Ограда (ח) разрушения (ש) — удержание (ך) без выхода. Ничто не проникает внутрь и не выходит наружу.",
      "meaning": "Тьма не как отсутствие света, а как сжатость материи. Непроницаемость, когда ничто не может войти или выйти.",
      "examples": ["изоляция", "эмоциональная глухота", "отчуждение"],
      "transitions": [
        { "to": "mitzrayim", "label": "найти грань", "action": "Определить, что именно давит — назвать это" },
        { "to": "midbar", "label": "прорвать ограду", "action": "Сделать шаг в неизвестность" }
      ],
      "diagnostic_questions": [
        { "id": "q_hoshekh_1", "text": "Чувствуешь ли ты давление со всех сторон?", "weight": { "hoshekh": 1.0, "mitzrayim": 0.5 } },
        { "id": "q_hoshekh_2", "text": "Есть ли ощущение, что ты отрезан от мира?", "weight": { "hoshekh": 0.9, "tohu": 0.3 } }
      ]
    },
    {
      "id": "mitzrayim",
      "name": "Мицраим",
      "hebrew": "מִצְרַיִם",
      "paleo": "𐤌𐤑𐤓𐤉𐤌",
      "color": "#5c2e1a",
      "physics": "Теснота. Стены (Хет), крюки (Вав) и двери, которые заперты. Нет движения — только циклы.",
      "intensity": 0.5,
      "intensity_label": "циклическое сжатие",
      "paleo_breakdown": [
        { "letter": "מ", "paleo": "𐤌", "name": "Мем", "function": "поток, течение" },
        { "letter": "צ", "paleo": "𐤑", "name": "Цаде", "function": "крюк, праведность" },
        { "letter": "ר", "paleo": "𐤓", "name": "Реш", "function": "голова, начало" },
        { "letter": "י", "paleo": "𐤉", "name": "Йод", "function": "рука, действие" },
        { "letter": "מ", "paleo": "𐤌", "name": "Мем", "function": "поток, течение" }
      ],
      "paleo_meaning": "Поток (מ) выхвачен крюком (צ) — поднят к вершине (ר) рукой (י) и перенаправлен в искусственный поток (מ). Рыбу выловили из естественного течения.",
      "meaning": "Городское сжатие. Пространство, где ты вынужден сжаться. Циклы: работа → сон → работа.",
      "examples": ["офисная рутина", "долговая яма", "токсичные отношения"],
      "transitions": [
        { "to": "midbar", "label": "разобрать заборы", "action": "Открыть двери, начать движение" },
        { "to": "eden", "label": "исход", "action": "Полный выход из системы сжатия" }
      ],
      "diagnostic_questions": [
        { "id": "q_mitz_1", "text": "Чувствуешь ли ты, что живёшь в цикле без развития?", "weight": { "mitzrayim": 1.0, "tohu": 0.3 } },
        { "id": "q_mitz_2", "text": "Есть ли ощущение, что тобой управляют внешние обстоятельства?", "weight": { "mitzrayim": 0.8, "hoshekh": 0.4 } }
      ]
    },
    {
      "id": "midbar",
      "name": "Мидбар",
      "hebrew": "מִדְבָּר",
      "paleo": "𐤌𐤃𐤁𐤓",
      "color": "#c4a44a",
      "physics": "Дикое открытое пространство. Есть Далет (дверь), но нет Бет (дома). Движение и калибровка.",
      "intensity": 0.6,
      "intensity_label": "открытое движение",
      "paleo_breakdown": [
        { "letter": "מ", "paleo": "𐤌", "name": "Мем", "function": "поток, течение" },
        { "letter": "ד", "paleo": "𐤃", "name": "Далет", "function": "дверь, проход" },
        { "letter": "ב", "paleo": "𐤁", "name": "Бет", "function": "дом, вместилище" },
        { "letter": "ר", "paleo": "𐤓", "name": "Реш", "function": "голова, начало" }
      ],
      "paleo_meaning": "Поток (מ) через дверь (ד) — дома (ב) нет, только начало (ר). Ты в движении, но ещё не построил убежище.",
      "meaning": "Пустыня как место калибровки. Ты идёшь, снимаешь слои, ищешь направление. Лес, пустыня, джунгли — естественные пространства, где ещё ничего не построено.",
      "examples": ["путешествие", "смена профессии", "период поиска"],
      "transitions": [
        { "to": "eden", "label": "достичь цели", "action": "Пройти калибровку, снять слои, достичь завершённости" },
        { "to": "erets", "label": "осесть", "action": "Найти опору и построить дом" }
      ],
      "diagnostic_questions": [
        { "id": "q_midbar_1", "text": "Находишься ли ты в периоде поиска и движения?", "weight": { "midbar": 1.0, "shamayim": 0.3 } },
        { "id": "q_midbar_2", "text": "Есть ли у тебя ощущение, что ты ещё не нашёл своё место?", "weight": { "midbar": 0.8, "erets": 0.3 } }
      ]
    },
    {
      "id": "shamayim",
      "name": "Шамаим",
      "hebrew": "שָׁמַיִם",
      "paleo": "𐤔𐤌𐤉𐤌",
      "color": "#4a6a9e",
      "physics": "Открытое пространство. Проницаемость. Небо как возможность видеть далеко.",
      "intensity": 0.75,
      "intensity_label": "открытость и проницаемость",
      "paleo_breakdown": [
        { "letter": "ש", "paleo": "𐤔", "name": "Шин", "function": "зуб, разрушение границ" },
        { "letter": "מ", "paleo": "𐤌", "name": "Мем", "function": "поток, течение" },
        { "letter": "י", "paleo": "𐤉", "name": "Йод", "function": "рука, действие" },
        { "letter": "מ", "paleo": "𐤌", "name": "Мем", "function": "поток, течение" }
      ],
      "paleo_meaning": "Разрушение границ (ש) — поток (מ) через действие (י) становится новым потоком (מ). Всё проницаемо.",
      "meaning": "Небеса как проницаемое пространство. Ты видишь далеко, дышишь свободно, границы не давят.",
      "examples": ["вдохновение", "ясность мысли", "свобода выбора"],
      "transitions": [
        { "to": "eden", "label": "пребывать", "action": "Оставаться в открытости и завершённости" },
        { "to": "erets", "label": "воплотить", "action": "Перенести открытость в материальную опору" }
      ],
      "diagnostic_questions": [
        { "id": "q_sham_1", "text": "Чувствуешь ли ты ясность и свободу?", "weight": { "shamayim": 1.0, "eden": 0.4 } },
        { "id": "q_sham_2", "text": "Видишь ли ты перспективу и варианты?", "weight": { "shamayim": 0.9, "midbar": 0.3 } }
      ]
    },
    {
      "id": "erets",
      "name": "Эрец",
      "hebrew": "אֶרֶץ",
      "paleo": "𐤀𐤓𐤑",
      "color": "#4a6a3a",
      "physics": "Опора. Основание. Земля под ногами. Устойчивость и материальность.",
      "intensity": 0.85,
      "intensity_label": "устойчивость и опора",
      "paleo_breakdown": [
        { "letter": "א", "paleo": "𐤀", "name": "Алеф", "function": "сила, начало" },
        { "letter": "ר", "paleo": "𐤓", "name": "Реш", "function": "голова, вершина" },
        { "letter": "ץ", "paleo": "𐤑", "name": "Цаде (софит)", "function": "крюк, цель" }
      ],
      "paleo_meaning": "Сила (א) направлена к вершине (ר) и закреплена (ץ). Земля как устойчивая опора под ногами.",
      "meaning": "Земля — не планета, а опора. То, на чём ты стоишь. Материальная база, корни, фундамент.",
      "examples": ["стабильный доход", "дом", "крепкие отношения"],
      "transitions": [
        { "to": "eden", "label": "расцвести", "action": "Из опоры вырастить плод" },
        { "to": "shamayim", "label": "подняться", "action": "От опоры к открытости" }
      ],
      "diagnostic_questions": [
        { "id": "q_erets_1", "text": "Чувствуешь ли ты твёрдую почву под ногами?", "weight": { "erets": 1.0, "eden": 0.3 } },
        { "id": "q_erets_2", "text": "Есть ли у тебя устойчивая опора в жизни?", "weight": { "erets": 0.9, "midbar": 0.2 } }
      ]
    },
    {
      "id": "eden",
      "name": "Эден",
      "hebrew": "עֵדֶן",
      "paleo": "𐤏𐤃𐤍",
      "color": "#d4a844",
      "physics": "Завершённое пространство. Далет уже открыта, и Бет наполнен жизнью. Жизнь течёт непрерывно.",
      "intensity": 1.0,
      "intensity_label": "завершённость и полнота",
      "paleo_breakdown": [
        { "letter": "ע", "paleo": "𐤏", "name": "Аин", "function": "глаз, видение, источник" },
        { "letter": "ד", "paleo": "𐤃", "name": "Далет", "function": "дверь, проход" },
        { "letter": "נ", "paleo": "𐤍", "name": "Нун", "function": "рыба, жизнь, движение" }
      ],
      "paleo_meaning": "Источник (ע) открывает дверь (ד), и жизнь (נ) течёт непрерывно. Сад, где всё уже завершено.",
      "meaning": "Сад завершённости. Ты просто находишься и видишь, потому что уже прибыл. Жизнь течёт без усилий.",
      "examples": ["состояние потока", "гармония", "плодоношение"],
      "transitions": [
        { "to": "shamayim", "label": "поделиться", "action": "Открыться новому, не теряя завершённости" },
        { "to": "erets", "label": "укоренить", "action": "Закрепить завершённость в материальном" }
      ],
      "diagnostic_questions": [
        { "id": "q_eden_1", "text": "Чувствуешь ли ты гармонию и завершённость?", "weight": { "eden": 1.0, "shamayim": 0.4 } },
        { "id": "q_eden_2", "text": "Течёт ли твоя жизнь естественно, без усилий?", "weight": { "eden": 0.9, "erets": 0.3 } }
      ]
    }
  ]
}