{
  "exposures": [
    {
      "id": "saturn",
      "title": "Сатурн — подмена святости",
      "hebrew_term": "שַׁבָּת (шаббат)",
      "substitution": "Сатурн → суббота → день Сатурна",
      "description": "Римляне заменили шаббат на день Сатурна, подменив святость на культ планеты",
      "chain": "шаббат (иврит) → sabbatum (латынь) → saturday (англ) → суббота (рус, от sabbatum)",
      "status": "draft"
    }
  ],
  "metadata": {
    "total": 0,
    "target_topics": ["Сатурн", "Apple", "BlackRock", "Никейский собор", "вавилонский культ"]
  }
}